
[
    {"id": 1, "name": "Lenovo", "img": "ImgProduct1", "price": 111, "stock": 5 },
    {"id": 2, "name": "Mac", "img": "ImgProduct2", "price": 3012,"stock": 4 },
    {"id": 3, "name": "Notebook 3 ", "img": "ImgProduct3", "price": 532, "stock": 3 },
    {"id": 4, "name": "Lenovo ThinkPad", "img": "ImgProduct4", "price": 954, "stock": 7 },
    {"id": 5, "name": "Arius", "img": "ImgProduct5", "price": 441, "stock": 8 },
    {"id": 6, "name": "Omega 3", "img": "ImgProduct6", "price": 652, "stock": 9 },
    {"id": 7, "name": "Potasio", "img": "ImgProduct7", "price": 1928,"stock": 2 },
    {"id": 8, "name": "Render", "img": "ImgProduct8", "price": 901, "stock": 6 },
    {"id": 9, "name": "object Object", "img": "ImgProduct9", "price": 301, "stock": 12 }
]
